phone_number_validator/__init__.py
phone_number_validator/validator.py
phone_number_validator_test_thing_i_guess-0.1.0.dist-info/METADATA
phone_number_validator_test_thing_i_guess-0.1.0.dist-info/WHEEL
phone_number_validator_test_thing_i_guess-0.1.0.dist-info/RECORD
