Metadata-Version: 2.1
Name: phone-number-validator-test-thing-i-guess
Version: 0.1.0
Summary: 
Author: Isaac Mierow
Author-email: mierowir@rose-hulman.edu
Requires-Python: >=3.10,<4.0
Classifier: Programming Language :: Python :: 3
Classifier: Programming Language :: Python :: 3.10
Classifier: Programming Language :: Python :: 3.11
Classifier: Programming Language :: Python :: 3.12
Requires-Dist: requests (>=2.31.0,<3.0.0)
